getids/__init__.py
getids/__main__.py
getids/ages.json
getids-1.1.0.dist-info/LICENSE
getids-1.1.0.dist-info/METADATA
getids-1.1.0.dist-info/WHEEL
getids-1.1.0.dist-info/top_level.txt
getids-1.1.0.dist-info/RECORD
