Metadata-Version: 2.1
Name: getids
Version: 1.1.0
Summary: A Python port of the GetIDs engine that calculates the date of creation for Telegram accounts using known creation dates.
Author-email: Amano LLC <contact@amanoteam.com>
License: MIT License
Project-URL: homepage, https://github.com/AmanoTeam/python-getids
Requires-Python: >=3.7
License-File: LICENSE
